{
  "fabric:load_conditions": [
    {
      "condition": "fabric:and",
      "values": [
        {
          "condition": "fabric:all_mods_loaded",
          "values": [
            "promenade"
          ]
        },
        {
          "condition": "fabric:registry_contains",
          "registry": "minecraft:block",
          "values": [
            "promenade:palm_planks"
          ]
        }
      ]
    }
  ],
  "type": "minecraft:crafting_shaped",
  "category": "misc",
  "key": {
    "#": {
      "item": "promenade:palm_planks"
    },
    "@": {
      "item": "minecraft:flint"
    }
  },
  "pattern": [
    "@@",
    "##",
    "##"
  ],
  "result": {
    "item": "variantfletchingtables:prom_palm_fletching_table"
  },
  "show_notification": true
}